README.txt
setup.cfg
setup.py
doc/Makefile
doc/make.bat
doc/source/ChangeLog.rst
doc/source/applications.rst
doc/source/authors.rst
doc/source/biblio.rst
doc/source/conf.py
doc/source/contribute.rst
doc/source/faqs.rst
doc/source/index.rst
doc/source/network.png
doc/source/quickstart.rst
doc/source/references.rst
doc/source/todo.rst
doc/source/userguide.rst
doc/source/_static/copybutton.js
share/data/MD-MultipleCellLines.csv
share/data/MD-Test.csv
share/data/MD-Test2.csv
share/data/MD-ToyMMB.csv
share/data/MD-average.csv
share/data/MD-one_exp.csv
share/data/MD-one_inhibitor.csv
share/data/MD-one_stimulus.csv
share/data/MD-test_1cue_noinhibitor.csv
share/data/MD-test_4andgates.csv
share/data/MD-test_diamond.csv
share/data/MD-unnorm.csv
share/data/MD-unnorm_exp.csv
share/data/MD-unnorm_exp_nozero.csv
share/data/PKN-Test.sif
share/data/PKN-TestAND.sif
share/data/PKN-ToyMMB.net
share/data/PKN-ToyMMB.sif
share/data/PKN-test_1cue_noinhibitor.sif
share/data/PKN-test_4andgates.sif
share/data/PKN-test_diamond.sif
share/data/README.txt
share/data/adjacency_matrix.csv
share/data/adjacency_names.csv
share/data/caspo_models.csv
share/data/data.sop
share/data/double.sif
share/data/kinetic.csv
share/data/metabolites
share/data/midas.xml
share/data/reactions
share/data/simple.eda
share/data/simple.sif
share/data/test_sbml.xml
share/data/XML/midas.xml
share/data/XML/midas.xsd
share/data/metabolites_samples/ExampleNetwIdent/app_para.m
share/data/metabolites_samples/ExampleNetwIdent/assembly
share/data/metabolites_samples/ExampleNetwIdent/examplenetwident.png
share/data/metabolites_samples/ExampleNetwIdent/examplenetwident_layout.dat
share/data/metabolites_samples/ExampleNetwIdent/macromolecule_synthesis
share/data/metabolites_samples/ExampleNetwIdent/macromolecules
share/data/metabolites_samples/ExampleNetwIdent/metabolites
share/data/metabolites_samples/ExampleNetwIdent/metabolites.simp
share/data/metabolites_samples/ExampleNetwIdent/metabolites.simplest
src/cellnopt.core.egg-info/PKG-INFO
src/cellnopt.core.egg-info/SOURCES.txt
src/cellnopt.core.egg-info/dependency_links.txt
src/cellnopt.core.egg-info/namespace_packages.txt
src/cellnopt.core.egg-info/not-zip-safe
src/cellnopt.core.egg-info/requires.txt
src/cellnopt.core.egg-info/top_level.txt
