Metadata-Version: 1.1
Name: cellnopt.core
Version: 1.0.0
Summary: Functions to manipulate networks and data related to signalling pathways.
Home-page: ['http://pythonhosted.org/cellnopt.core/']
Author: Thomas Cokelaer
Author-email: cokelaer@ebi.ac.uk
License: GPL
Download-URL: ['http://pypi.python.org/pypi/cellnopt.core']
Keywords: SIF,MIDAS,SOP,Kinexus,CellNOpt,CNOGraph
Platform: Linux
Platform: Unix
Platform: MacOsX
Platform: Windows
Classifier: Development Status :: 7 - Inactive
Classifier: Intended Audience :: Developers
Classifier: Intended Audience :: Science/Research
Classifier: License :: OSI Approved :: GNU Library or Lesser General Public License (LGPL)
Classifier: Operating System :: OS Independent
Classifier: Programming Language :: Python :: 2.7
Classifier: Topic :: Software Development :: Libraries :: Python Modules
Classifier: Topic :: Scientific/Engineering :: Bio-Informatics
Classifier: Topic :: Scientific/Engineering :: Information Analysis
Classifier: Topic :: Scientific/Engineering :: Mathematics
Classifier: Topic :: Scientific/Engineering :: Physics
